{
  "latest": {
    "version": "0.15.0",
    "releaseDate": "2025-02-12",
    "firmwareUrl": "https://example.com/firmware/firmware_v0.2.0.bin",  // Acho que achei um jeito, colocar o link do github para baixar o firmware
    "releaseNotes": "Correções de bugs e melhorias de desempenho.",
    "changelog": [
      "Adicionado",
      "- Implementado comunicação com aplicação do computador 🎉",
      "- Funções a biblioteca de botões",
      "- Funções de requisição",
      "Alterado",
      "- Organização do programa",
      "Consertado",
      "- Configurações não salvavam"
    ]
  },
  "olders": [
    {
      "id": 1,
      "version": "0.1.0",
      "releaseDate": "2025-01-28",
      "firmwareUrl": "https://example.com/firmware/firmware_v0.1.0.bin",  // Acho que achei um jeito, colocar o link do github para baixar o firmware
      "releaseNotes": "Correções de bugs e melhorias de desempenho.",
      "changelog": [
        "Adicionado",
        "- Páginas principais",
        "- Funcionalidades na página"
      ]
    },
    {
      "id": 2,
      "version": "0.0.5",
      "releaseDate": "2025-01-20",
      "firmwareUrl": "https://example.com/firmware/firmware_v0.0.5.bin",  // Acho que achei um jeito, colocar o link do github para baixar o firmware
      "releaseNotes": "Correções de bugs e melhorias de desempenho.",
      "changelog": [
        "Início do projeto",
        "- Criação do layout",
        "- Configuração do banco de dados"
      ]
    }
  ]
}
